MANIFEST.in
README.rst
VERSION.txt
pyproject.toml
requirements.txt
setup.cfg
setup.py
tox.ini
bin/math-readline
bin/sage
bin/sage-cachegrind
bin/sage-callgrind
bin/sage-cleaner
bin/sage-coverage
bin/sage-cython
bin/sage-env
bin/sage-env-config
bin/sage-env-config.in
bin/sage-eval
bin/sage-fixdoctests
bin/sage-gdb-commands
bin/sage-grep
bin/sage-grepdoc
bin/sage-inline-fortran
bin/sage-ipynb2rst
bin/sage-ipython
bin/sage-list-packages
bin/sage-location
bin/sage-massif
bin/sage-native-execute
bin/sage-notebook
bin/sage-num-threads.py
bin/sage-omega
bin/sage-open
bin/sage-preparse
bin/sage-python
bin/sage-rebase.bat
bin/sage-rebase.sh
bin/sage-rebaseall.bat
bin/sage-rebaseall.sh
bin/sage-run
bin/sage-run-cython
bin/sage-runtests
bin/sage-src-env-config.in
bin/sage-startuptime.py
bin/sage-update-src
bin/sage-update-version
bin/sage-valgrind
bin/sage-venv-config
bin/sage-version.sh
sage/__init__.py
sage/all__sagemath_categories.py
sage/all__sagemath_objects.py
sage/all__sagemath_polyhedra.py
sage/env.py
sage/version.py
sage/arith/__init__.py
sage/arith/all.py
sage/arith/constants.pxd
sage/arith/functions.pxd
sage/arith/functions.pyx
sage/arith/long.pxd
sage/arith/misc.py
sage/arith/multi_modular.pxd
sage/arith/multi_modular.pyx
sage/arith/numerical_approx.pxd
sage/arith/numerical_approx.pyx
sage/arith/power.pxd
sage/arith/power.pyx
sage/arith/rational_reconstruction.pxd
sage/arith/rational_reconstruction.pyx
sage/arith/srange.pyx
sage/categories/__init__.py
sage/categories/action.pxd
sage/categories/action.pyx
sage/categories/additive_groups.py
sage/categories/additive_magmas.py
sage/categories/additive_monoids.py
sage/categories/additive_semigroups.py
sage/categories/affine_weyl_groups.py
sage/categories/algebra_functor.py
sage/categories/algebra_ideals.py
sage/categories/algebra_modules.py
sage/categories/algebras.py
sage/categories/algebras_with_basis.py
sage/categories/all.py
sage/categories/all__sagemath_objects.py
sage/categories/aperiodic_semigroups.py
sagemath_polyhedra.egg-info/PKG-INFO
sagemath_polyhedra.egg-info/SOURCES.txt
sagemath_polyhedra.egg-info/dependency_links.txt
sagemath_polyhedra.egg-info/requires.txt
sagemath_polyhedra.egg-info/top_level.txt