Metadata-Version: 2.1
Name: sagemath-polyhedra
Version: 9.5b6
Summary: Sage: Open Source Mathematics Software: Convex polyhedra in arbitrary dimension
Home-page: https://www.sagemath.org
Author: The Sage Developers
Author-email: sage-support@googlegroups.com
License: GNU General Public License (GPL) v2 or later
Platform: UNKNOWN
Classifier: Development Status :: 6 - Mature
Classifier: Intended Audience :: Education
Classifier: Intended Audience :: Science/Research
Classifier: License :: OSI Approved :: GNU General Public License v2 or later (GPLv2+)
Classifier: Operating System :: POSIX
Classifier: Operating System :: MacOS :: MacOS X
Classifier: Programming Language :: Python :: 3 :: Only
Classifier: Programming Language :: Python :: 3.7
Classifier: Programming Language :: Python :: 3.8
Classifier: Programming Language :: Python :: 3.9
Classifier: Programming Language :: Python :: Implementation :: CPython
Classifier: Topic :: Scientific/Engineering :: Mathematics
Requires-Python: <3.11,>=3.7
